ibroadcast/__init__.py
ibroadcast/about.py
ibroadcast/ibroadcast.py
ibroadcast/util.py
ibroadcast-1.1.2.dist-info/METADATA
ibroadcast-1.1.2.dist-info/WHEEL
ibroadcast-1.1.2.dist-info/top_level.txt
ibroadcast-1.1.2.dist-info/RECORD
