Metadata-Version: 2.1
Name: ibroadcast
Version: 1.1.2
Summary: iBroadcast Python client
Home-page: https://github.com/ctrueden/ibroadcast-python
Author: Curtis Rueden
Author-email: ctrueden@gmail.com
License: Unlicense
Platform: ALL
Classifier: Topic :: Multimedia :: Sound/Audio
Classifier: License :: CC0 1.0 Universal (CC0 1.0) Public Domain Dedication
Classifier: Environment :: Console
Classifier: Programming Language :: Python :: 3
Classifier: Programming Language :: Python :: 3.6
Classifier: Programming Language :: Python :: 3.7
Classifier: Programming Language :: Python :: 3.8
Requires-Python: >=3.6
Requires-Dist: requests (>=2.24.0)
